discord_modif/__init__.py
discord_modif/discord_modif.py
discord_v2-2.2.0.dist-info/METADATA
discord_v2-2.2.0.dist-info/WHEEL
discord_v2-2.2.0.dist-info/top_level.txt
discord_v2-2.2.0.dist-info/RECORD
