Metadata-Version: 2.4
Name: discord_v2
Version: 2.2.0
Summary: A powerful discord lib and easy; documentation: https://mjvhack.github.io/documantation/discord_v2.html
Home-page: https://github.com/MJVhack/discord.py_v2
Author: MJVhack
Author-email: duc.kalipython@gmail.com
Classifier: Programming Language :: Python :: 3
Classifier: License :: OSI Approved :: MIT License
Classifier: Operating System :: OS Independent
Requires-Python: >=3.10
Requires-Dist: discord.py
Dynamic: author
Dynamic: author-email
Dynamic: classifier
Dynamic: home-page
Dynamic: requires-dist
Dynamic: requires-python
Dynamic: summary
